ntnx_networking_py_client/__init__.py
ntnx_networking_py_client/api_client.py
ntnx_networking_py_client/api_response.py
ntnx_networking_py_client/configuration.py
ntnx_networking_py_client/custom_retry.py
ntnx_networking_py_client/rest.py
ntnx_networking_py_client/api/__init__.py
ntnx_networking_py_client/api/aws_subnets_api.py
ntnx_networking_py_client/api/aws_vpcs_api.py
ntnx_networking_py_client/api/bgp_routes_api.py
ntnx_networking_py_client/api/bgp_sessions_api.py
ntnx_networking_py_client/api/bridges_api.py
ntnx_networking_py_client/api/cluster_capabilities_api.py
ntnx_networking_py_client/api/floating_ips_api.py
ntnx_networking_py_client/api/gateways_api.py
ntnx_networking_py_client/api/ipfix_exporters_api.py
ntnx_networking_py_client/api/layer2_stretch_stats_api.py
ntnx_networking_py_client/api/layer2_stretches_api.py
ntnx_networking_py_client/api/load_balancer_session_stats_api.py
ntnx_networking_py_client/api/load_balancer_sessions_api.py
ntnx_networking_py_client/api/mac_addresses_api.py
ntnx_networking_py_client/api/network_controllers_api.py
ntnx_networking_py_client/api/network_functions_api.py
ntnx_networking_py_client/api/nic_profiles_api.py
ntnx_networking_py_client/api/remote_entities_api.py
ntnx_networking_py_client/api/route_tables_api.py
ntnx_networking_py_client/api/routes_api.py
ntnx_networking_py_client/api/routing_policies_api.py
ntnx_networking_py_client/api/routing_policy_stats_api.py
ntnx_networking_py_client/api/subnet_ip_reservation_api.py
ntnx_networking_py_client/api/subnet_migrations_api.py
ntnx_networking_py_client/api/subnets_api.py
ntnx_networking_py_client/api/traffic_mirror_stats_api.py
ntnx_networking_py_client/api/traffic_mirrors_api.py
ntnx_networking_py_client/api/uplink_bonds_api.py
ntnx_networking_py_client/api/virtual_switch_nodes_info_api.py
ntnx_networking_py_client/api/virtual_switches_api.py
ntnx_networking_py_client/api/vpc_ns_stats_api.py
ntnx_networking_py_client/api/vpc_virtual_switch_mappings_api.py
ntnx_networking_py_client-4.2.1.dist-info/LICENSE.txt
ntnx_networking_py_client-4.2.1.dist-info/METADATA
ntnx_networking_py_client-4.2.1.dist-info/WHEEL
ntnx_networking_py_client-4.2.1.dist-info/top_level.txt
ntnx_networking_py_client-4.2.1.dist-info/RECORD
